prometheus_client_utils/__init__.py
prometheus_client_utils/collectors/__init__.py
prometheus_client_utils/collectors/asyncio_loop.py
prometheus_client_utils/collectors/push_clients.py
prometheus_client_utils/push_clients/__init__.py
prometheus_client_utils/push_clients/base.py
prometheus_client_utils/push_clients/pushgateway.py
prometheus_client_utils/push_clients/statsd.py
prometheus_client_utils-0.1.3.dist-info/LICENSE
prometheus_client_utils-0.1.3.dist-info/METADATA
prometheus_client_utils-0.1.3.dist-info/WHEEL
prometheus_client_utils-0.1.3.dist-info/RECORD
