Metadata-Version: 2.1
Name: prometheus-client-utils
Version: 0.1.3
Summary: Utils fot prometheus-client
Home-page: https://gitlab.com/rocshers/python/prometheus-client-utils
License: MIT
Author: aleksei.marusich
Author-email: aleksei.marusich@rocshers.com
Requires-Python: >=3.8,<4.0
Classifier: Intended Audience :: Developers
Classifier: Intended Audience :: Information Technology
Classifier: Intended Audience :: System Administrators
Classifier: License :: OSI Approved :: MIT License
Classifier: Programming Language :: Python
Classifier: Programming Language :: Python :: 3
Classifier: Programming Language :: Python :: 3.8
Classifier: Programming Language :: Python :: 3.9
Classifier: Programming Language :: Python :: 3.10
Classifier: Programming Language :: Python :: 3.11
Classifier: Programming Language :: Python :: 3 :: Only
Classifier: Topic :: Software Development
Classifier: Topic :: Software Development :: Libraries
Classifier: Topic :: Software Development :: Libraries :: Python Modules
Classifier: Topic :: System :: Archiving :: Packaging
Classifier: Topic :: System :: Installation/Setup
Classifier: Topic :: System :: Software Distribution
Requires-Dist: prometheus-client
Project-URL: Repository, https://gitlab.com/rocshers/python/prometheus-client-utils
